lele/__init__.py
lele/cli.py
lele/models/prompt.py
lele-0.1.5.dist-info/METADATA
lele-0.1.5.dist-info/WHEEL
lele-0.1.5.dist-info/entry_points.txt
lele-0.1.5.dist-info/RECORD
