Metadata-Version: 2.3
Name: lele
Version: 0.1.5
Summary: Add your description here
Author-email: Zen Tang <ztang230@gmail.com>
Requires-Python: >=3.8
Requires-Dist: click>=8.1.7
Requires-Dist: colorama>=0.4.6
Requires-Dist: pydantic>=2.6.4
Requires-Dist: requests>=2.31.0
